MANIFEST.in
README.rst
setup.cfg
setup.py
./include/ketch.h
./src/Ketcham.c
pyAFT/__init__.py
pyAFT/annealing.py
pyAFT/parameters.py
pyAFT/pyAFT.py
pyAFT/radialplot.py
pyAFT/utilities.py
pyAFT.egg-info/PKG-INFO
pyAFT.egg-info/SOURCES.txt
pyAFT.egg-info/dependency_links.txt
pyAFT.egg-info/requires.txt
pyAFT.egg-info/top_level.txt
pyAFT/thermal_histories/__init__.py
pyAFT/thermal_histories/thermal_histories.py